jk_argparsing/ArgCommand.py
jk_argparsing/ArgItemBase.py
jk_argparsing/ArgOption.py
jk_argparsing/ArgUtils.py
jk_argparsing/ArgsOptionDataDict.py
jk_argparsing/ArgsParser.py
jk_argparsing/AvailableLicenseList.py
jk_argparsing/BashCompletionLocal.py
jk_argparsing/EnumParameterType.py
jk_argparsing/LicenseInfo.py
jk_argparsing/OptionParameter.py
jk_argparsing/ParsedArgs.py
jk_argparsing/__init__.py
jk_argparsing/__OLD/_DescrChapter.py
jk_argparsing/__OLD/_DescrPargraph.py
jk_argparsing/impl/HelpTextBuilder.py
jk_argparsing/impl/HelpTextData.py
jk_argparsing/impl/ImplementationErrorException.py
jk_argparsing/impl/__init__.py
jk_argparsing/textmodel/TBlock.py
jk_argparsing/textmodel/TList.py
jk_argparsing/textmodel/TSection.py
jk_argparsing/textmodel/VisSettings.py
jk_argparsing/textmodel/__init__.py
jk_argparsing/textmodel/__OLD/TextSequence.py
jk_argparsing/textmodel/__OLD/TextTitledSection.py
jk_argparsing/textprimitives/ITextBlock.py
jk_argparsing/textprimitives/TextBlock.py
jk_argparsing/textprimitives/TextBlockSequence.py
jk_argparsing/textprimitives/TextColumnsBlock.py
jk_argparsing/textprimitives/TextEmpty.py
jk_argparsing/textprimitives/TextGridBlock.py
jk_argparsing/textprimitives/TextPrefixBlock.py
jk_argparsing/textprimitives/XLineFragment.py
jk_argparsing/textprimitives/__init__.py
jk_argparsing/textprimitives/columnLayouterL2R.py
jk_argparsing-0.2024.11.20.1.dist-info/LICENSE.txt
jk_argparsing-0.2024.11.20.1.dist-info/WHEEL
jk_argparsing-0.2024.11.20.1.dist-info/METADATA
jk_argparsing-0.2024.11.20.1.dist-info/RECORD
