Metadata-Version: 2.1
Name: jk_argparsing
Version: 0.2024.11.20.1
Summary: A python module for parsing of program arguments.
Keywords: program,arguments,commands,options,args
Author-email: Jürgen Knauth <pubsrc@binary-overflow.de>
Requires-Python: >=3.8
Classifier: Development Status :: 5 - Production/Stable
Classifier: Programming Language :: Python
Classifier: Programming Language :: Python :: 3
Classifier: Environment :: Console
Classifier: License :: OSI Approved :: Apache Software License
Requires-Dist: jk_terminal_essentials >= 0.2024.2.2
Project-URL: Home, https://github.com/jkpubsrc/python-module-jk-argparsing
Project-URL: Homepage, https://github.com/jkpubsrc/python-module-jk-argparsing
